[
  {
    "number": "1",
    "name": "Roll (ロール)",
    "type": "None",
    "damage": 20,
    "possibleCodes": "",
    "memory": 0,
    "description": "Attacks enmy, then heals you",
    "locations": "Obtained in email from Mayl Sakurai during the story. Reward from request \"Track the Criminal\"."
  },
  {
    "number": "2",
    "name": "Roll2 (ロール２)",
    "type": "None",
    "damage": 40,
    "possibleCodes": "",
    "memory": 0,
    "description": "Attacks enmy, then heals you",
    "locations": "Obtained in email from Mayl during the story."
  },
  {
    "number": "3",
    "name": "Roll3 (ロール３)",
    "type": "None",
    "damage": 60,
    "possibleCodes": "",
    "memory": 0,
    "description": "Attacks enmy, then heals you",
    "locations": "Talk to Mayl in Lan\u0027s house during the final chapter of the game."
  },
  {
    "number": "4",
    "name": "ProtoMan (ブルース)",
    "type": "Sword",
    "damage": 150,
    "possibleCodes": "",
    "memory": 0,
    "description": "Move in and slice the enemy",
    "locations": "ProtoMan v1/EX/SP Reward from request \"Track the Criminal\""
  },
  {
    "number": "5",
    "name": "ProtoMnEX (ブルースＥＸ)",
    "type": "Sword",
    "damage": 170,
    "possibleCodes": "",
    "memory": 0,
    "description": "Move in and slice the enemy",
    "locations": "ProtoMan EX/SP"
  },
  {
    "number": "6",
    "name": "ProtoMnSP (ブルースＳＰ)",
    "type": "Sword",
    "damage": 190,
    "possibleCodes": "",
    "memory": 0,
    "description": "Move in and slice the enemy",
    "locations": "ProtoMan SP"
  },
  {
    "number": "22",
    "name": "BlastMan (ブラストマン)",
    "type": "Heat",
    "damage": 120,
    "possibleCodes": "",
    "memory": 0,
    "description": "Head fwd \u0026 launch blst attk",
    "locations": "BlastMan EX/SP Lotto Number 24616497"
  },
  {
    "number": "23",
    "name": "BlastMnEX (ブラストマンＥＸ)",
    "type": "Heat",
    "damage": 140,
    "possibleCodes": "",
    "memory": 0,
    "description": "Head fwd \u0026 launch blst attk",
    "locations": "BlastMan EX/SP"
  },
  {
    "number": "24",
    "name": "BlastMnSP (ブラストマンＳＰ)",
    "type": "Heat",
    "damage": 150,
    "possibleCodes": "",
    "memory": 0,
    "description": "Head fwd \u0026 launch blst attk",
    "locations": "BlastMan SP"
  },
  {
    "number": "25",
    "name": "DiveMan (ダイブマン)",
    "type": "Aqua",
    "damage": 130,
    "possibleCodes": "",
    "memory": 0,
    "description": "Snd giant wave acrs area 2pnl",
    "locations": "DiveMan EX/SP Lotto Number 32310827"
  },
  {
    "number": "26",
    "name": "DiveManEX (ダイブマンＥＸ)",
    "type": "Aqua",
    "damage": 150,
    "possibleCodes": "",
    "memory": 0,
    "description": "Snd giant wave acrs area 2pnl",
    "locations": "DiveMan EX/SP"
  },
  {
    "number": "27",
    "name": "DiveManSP (ダイブマンＳＰ)",
    "type": "Aqua",
    "damage": 170,
    "possibleCodes": "",
    "memory": 0,
    "description": "Snd giant wave acrs area 2pnl",
    "locations": "DiveMan SP"
  },
  {
    "number": "28",
    "name": "CrcusMan (サーカスマン)",
    "type": "None",
    "damage": 20,
    "possibleCodes": "",
    "memory": 0,
    "description": "Capture enmy in a ash attck",
    "locations": "CircusMan EX/SP Reward from request \"An Experiment!\""
  },
  {
    "number": "29",
    "name": "CrcusMnEX (サーカスマンＥＸ)",
    "type": "None",
    "damage": 25,
    "possibleCodes": "",
    "memory": 0,
    "description": "Capture enmy in a ash attck",
    "locations": "CircusMan EX/SP"
  },
  {
    "number": "30",
    "name": "CrcusMnSP (サーカスマンＳＰ)",
    "type": "None",
    "damage": 30,
    "possibleCodes": "",
    "memory": 0,
    "description": "Capture enmy in a ash attck",
    "locations": "CircusMan SP"
  },
  {
    "number": "31",
    "name": "JudgeMan (ジャッジマン)",
    "type": "Elec",
    "damage": 100,
    "possibleCodes": "",
    "memory": 0,
    "description": "Whip 3 panels forward",
    "locations": "JudgeMan EX/SP Reward from request \"An Experiment!\""
  },
  {
    "number": "32",
    "name": "JudgeMnEX (ジャッジマンＥＸ)",
    "type": "Elec",
    "damage": 120,
    "possibleCodes": "",
    "memory": 0,
    "description": "Whip 3 panels forward",
    "locations": "JudgeMan EX/SP"
  },
  {
    "number": "33",
    "name": "JudgeMnSP (ジャッジマンＳＰ)",
    "type": "Elec",
    "damage": 140,
    "possibleCodes": "",
    "memory": 0,
    "description": "Whip 3 panels forward",
    "locations": "JudgeMan SP"
  },
  {
    "number": "34",
    "name": "ElmntMan (エレメントマン)",
    "type": "None",
    "damage": 100,
    "possibleCodes": "",
    "memory": 0,
    "description": "Hit (A) whn col chges elem attk",
    "locations": "ElementMan EX/SP Reward from request \"An Experiment!\""
  },
  {
    "number": "35",
    "name": "ElmntMnEX (エレメントマンＥＸ)",
    "type": "None",
    "damage": 120,
    "possibleCodes": "",
    "memory": 0,
    "description": "Hit (A) whn col chges elem attk",
    "locations": "ElementMan EX/SP"
  },
  {
    "number": "36",
    "name": "ElmntMnSP (エレメントマンＳＰ)",
    "type": "None",
    "damage": 140,
    "possibleCodes": "",
    "memory": 0,
    "description": "Hit (A) whn col chges elem attk",
    "locations": "ElementMan SP"
  },
  {
    "number": "37",
    "name": "Colonel (カーネル)",
    "type": "Sword",
    "damage": 160,
    "possibleCodes": "",
    "memory": 0,
    "description": "Cut enmy lines in Z shape",
    "locations": "Colonel EX/SP Reward from request \"Track the criminal\""
  },
  {
    "number": "38",
    "name": "ColonelEX (カーネルＥＸ)",
    "type": "Sword",
    "damage": 180,
    "possibleCodes": "",
    "memory": 0,
    "description": "Cut enmy lines in Z shape",
    "locations": "Colonel EX/SP"
  },
  {
    "number": "39",
    "name": "ColonelSP (カーネルＳＰ)",
    "type": "Sword",
    "damage": 200,
    "possibleCodes": "",
    "memory": 0,
    "description": "Cut enmy lines in Z shape",
    "locations": "Colonel SP"
  },
  {
    "number": "7",
    "name": "SpoutMan (アクアマン)",
    "type": "Aqua",
    "damage": 50,
    "possibleCodes": "",
    "memory": 0,
    "description": "Watr atk! Bhnd 2row power-up",
    "locations": "SpoutMan v1/EX/SP Lotto Number 51702791. (Falzar exclusive)"
  },
  {
    "number": "8",
    "name": "SpoutMnEX (アクアマンＥＸ)",
    "type": "Aqua",
    "damage": 60,
    "possibleCodes": "",
    "memory": 0,
    "description": "Watr atk! Bhnd 2row power-up",
    "locations": "SpoutMan EX/SP. (Falzar exclusive)"
  },
  {
    "number": "9",
    "name": "SpoutMnSP (アクアマンＳＰ)",
    "type": "Aqua",
    "damage": 70,
    "possibleCodes": "",
    "memory": 0,
    "description": "Watr atk! Bhnd 2row power-up",
    "locations": "SpoutMan SP. (Falzar exclusive)"
  },
  {
    "number": "10",
    "name": "TmhkMan (トマホークマン)",
    "type": "Wood",
    "damage": 140,
    "possibleCodes": "",
    "memory": 0,
    "description": "Slice 2sq side, 3sq vertical",
    "locations": "TomahawkMan v1/EX/SP Lotto Number 67520179. (Falzar exclusive)"
  },
  {
    "number": "11",
    "name": "TmhkManEX (トマホークマンＥＸ)",
    "type": "Wood",
    "damage": 160,
    "possibleCodes": "",
    "memory": 0,
    "description": "Slice 2sq side, 3sq vertical",
    "locations": "TomahawkMan EX/SP. (Falzar exclusive)"
  },
  {
    "number": "12",
    "name": "TmhkManSP (トマホークマンＳＰ)",
    "type": "Wood",
    "damage": 180,
    "possibleCodes": "",
    "memory": 0,
    "description": "Slice 2sq side, 3sq vertical",
    "locations": "TomahawkMan SP. (Falzar exclusive)"
  },
  {
    "number": "13",
    "name": "TenguMan (テングマン)",
    "type": "Wind",
    "damage": 70,
    "possibleCodes": "",
    "memory": 0,
    "description": "Attk 2row from air, then side",
    "locations": "TenguMan v1/EX/SP Lotto Number 00297421. (Falzar exclusive)"
  },
  {
    "number": "14",
    "name": "TenguMnEX (テングマンＥＸ)",
    "type": "Wind",
    "damage": 90,
    "possibleCodes": "",
    "memory": 0,
    "description": "Attk 2row from air, then side",
    "locations": "TenguMan EX/SP. (Falzar exclusive)"
  },
  {
    "number": "15",
    "name": "TenguMnSP (テングマンＳＰ)",
    "type": "Wind",
    "damage": 110,
    "possibleCodes": "",
    "memory": 0,
    "description": "Attk 2row from air, then side",
    "locations": "TenguMan SP. (Falzar exclusive)"
  },
  {
    "number": "16",
    "name": "GrndMan (グランドマン)",
    "type": "Break",
    "damage": 60,
    "possibleCodes": "",
    "memory": 0,
    "description": "Move fwrd then attk w/ drill",
    "locations": "GroundMan v1/EX/SP Lotto Number 10414878. (Falzar exclusive)"
  },
  {
    "number": "17",
    "name": "GrndManEX (グランドマンＥＸ)",
    "type": "Break",
    "damage": 70,
    "possibleCodes": "",
    "memory": 0,
    "description": "Move fwrd then attk w/ drill",
    "locations": "GroundMan EX/SP. (Falzar exclusive)"
  },
  {
    "number": "18",
    "name": "GrndManSP (グランドマンＳＰ)",
    "type": "Break",
    "damage": 80,
    "possibleCodes": "",
    "memory": 0,
    "description": "Move fwrd then attk w/ drill",
    "locations": "GroundMan SP. (Falzar exclusive)"
  },
  {
    "number": "19",
    "name": "DustMan (ダストマン)",
    "type": "None",
    "damage": 110,
    "possibleCodes": "",
    "memory": 0,
    "description": "Attk ahd. Suck in \u0026 shoot out",
    "locations": "DustMan v1/EX/SP Lotto Number 79814666. (Falzar exclusive)"
  },
  {
    "number": "20",
    "name": "DustManEX (ダストマンＥＸ)",
    "type": "None",
    "damage": 130,
    "possibleCodes": "",
    "memory": 0,
    "description": "Attk ahd. Suck in \u0026 shoot out",
    "locations": "DustMan EX/SP. (Falzar exclusive)"
  },
  {
    "number": "21",
    "name": "DustManSP (ダストマンＳＰ)",
    "type": "None",
    "damage": 150,
    "possibleCodes": "",
    "memory": 0,
    "description": "Attk ahd. Suck in \u0026 shoot out",
    "locations": "DustMan SP. (Falzar exclusive)"
  },
  {
    "number": "7",
    "name": "HeatMan (ヒートマン)",
    "type": "Heat",
    "damage": 100,
    "possibleCodes": "",
    "memory": 0,
    "description": "Burn with a radial fire attk",
    "locations": "HeatMan v1/EX/SP Lotto Number 12404002. (Gregar exclusive)"
  },
  {
    "number": "8",
    "name": "HeatManEX (ヒートマンＥＸ)",
    "type": "Heat",
    "damage": 130,
    "possibleCodes": "",
    "memory": 0,
    "description": "Burn with a radial fire attk",
    "locations": "HeatMan EX/SP. (Gregar exclusive)"
  },
  {
    "number": "9",
    "name": "HeatManSP (ヒートマンＳＰ)",
    "type": "Heat",
    "damage": 160,
    "possibleCodes": "",
    "memory": 0,
    "description": "Burn with a radial fire attk",
    "locations": "HeatMan SP. (Gregar exclusive)"
  },
  {
    "number": "10",
    "name": "ElecMan (エレキマン)",
    "type": "Elec",
    "damage": 120,
    "possibleCodes": "",
    "memory": 0,
    "description": "Attk your surrndns with thdr",
    "locations": "ElecMan v1/EX/SP Lotto Number 30424514. (Gregar exclusive)"
  },
  {
    "number": "11",
    "name": "ElecManEX (エレキマンＥＸ)",
    "type": "Elec",
    "damage": 140,
    "possibleCodes": "",
    "memory": 0,
    "description": "Attk your surrndns with thdr",
    "locations": "ElecMan EX/SP. (Gregar exclusive)"
  },
  {
    "number": "12",
    "name": "ElecManSP (エレキマンＳＰ)",
    "type": "Elec",
    "damage": 160,
    "possibleCodes": "",
    "memory": 0,
    "description": "Attk your surrndns with thdr",
    "locations": "ElecMan SP. (Gregar exclusive)"
  },
  {
    "number": "13",
    "name": "SlashMan (スラッシュマン)",
    "type": "Sword",
    "damage": 80,
    "possibleCodes": "",
    "memory": 0,
    "description": "Slash an enmy w/ flyn knfe",
    "locations": "SlashMan v1/EX/SP Lotto Number 55910601. (Gregar exclusive)"
  },
  {
    "number": "14",
    "name": "SlashMnEX (スラッシュマンＥＸ)",
    "type": "Sword",
    "damage": 100,
    "possibleCodes": "",
    "memory": 0,
    "description": "Slash an enmy w/ flyn knfe",
    "locations": "SlashMan EX/SP. (Gregar exclusive)"
  },
  {
    "number": "15",
    "name": "SlashMnSP (スラッシュマンＳＰ)",
    "type": "Sword",
    "damage": 120,
    "possibleCodes": "",
    "memory": 0,
    "description": "Slash an enmy w/ flyn knfe",
    "locations": "SlashMan SP. (Gregar exclusive)"
  },
  {
    "number": "16",
    "name": "EraseMan (キラーマン)",
    "type": "Cursor",
    "damage": 120,
    "possibleCodes": "",
    "memory": 0,
    "description": "Press (A) for 3panl beam attk",
    "locations": "EraseMan v1/EX/SP Lotto Number 84387543. (Gregar exclusive)"
  },
  {
    "number": "17",
    "name": "EraseMnEX (キラーマンＥＸ)",
    "type": "Cursor",
    "damage": 140,
    "possibleCodes": "",
    "memory": 0,
    "description": "Press (A) for 3panl beam attk",
    "locations": "EraseMan EX/SP. (Gregar exclusive)"
  },
  {
    "number": "18",
    "name": "EraseMnSP (キラーマンＳＰ)",
    "type": "Cursor",
    "damage": 160,
    "possibleCodes": "",
    "memory": 0,
    "description": "Press (A) for 3panl beam attk",
    "locations": "EraseMan SP. (Gregar exclusive)"
  },
  {
    "number": "19",
    "name": "ChrgeMan (チャージマン)",
    "type": "None",
    "damage": 60,
    "possibleCodes": "",
    "memory": 0,
    "description": "Rush fwd! Open panl hit TrCar",
    "locations": "ChargeMan v1/EX/SP Lotto Number 92070765. (Gregar exclusive)"
  },
  {
    "number": "20",
    "name": "ChrgeMnEX (チャージマンＥＸ)",
    "type": "None",
    "damage": 70,
    "possibleCodes": "",
    "memory": 0,
    "description": "Rush fwd! Open panl hit TrCar",
    "locations": "ChargeMan EX/SP. (Gregar exclusive)"
  },
  {
    "number": "21",
    "name": "ChrgeMnSP (チャージマンＳＰ)",
    "type": "None",
    "damage": 80,
    "possibleCodes": "",
    "memory": 0,
    "description": "Rush fwd! Open panl hit TrCar",
    "locations": "ChargeMan SP. (Gregar exclusive)"
  }
]
